backend/api/__init__.py
backend/api/code.py
backend/api/device_actions.py
backend/api/devices.py
backend/api/element.py
backend/api/recorder.py
backend/api/screenshot.py
backend/api/ui_hierarchy.py
backend/api/websocket.py
backend/core/__init__.py
backend/core/advanced_detector.py
backend/core/bar_chart_detector.py
backend/core/basic_detector.py
backend/core/chinese_display_test.py
backend/core/clean_final_visualization.py
backend/core/complete_final_visualization.py
backend/core/complete_with_icons_visualization.py
backend/core/comprehensive_detector.py
backend/core/comprehensive_test.py
backend/core/corrected_icon_detector.py
backend/core/corrected_visualization.py
backend/core/definitive_lightning_detector.py
backend/core/enhanced_complete_visualization.py
backend/core/enhanced_icon_detector.py
backend/core/enhanced_ocr_corrector.py
backend/core/final_comprehensive_test.py
backend/core/final_comprehensive_visualization.py
backend/core/final_corrected_visualization.py
backend/core/final_lightning_detector.py
backend/core/final_lightning_visualization.py
backend/core/fix_chinese_display.py
backend/core/fix_specific_ocr_issues.py
backend/core/full_pipeline_visualization.py
backend/core/icon_detector.py
backend/core/improved_icon_detector.py
backend/core/improved_signal_detector.py
backend/core/lightning_focused_detector.py
backend/core/lightning_location_finder.py
backend/core/non_overlapping_detector.py
backend/core/perfect_final_visualization.py
backend/core/pixel_level_lightning_finder.py
backend/core/precise_circle_detector.py
backend/core/precise_lightning_detection.py
backend/core/precise_lightning_locator.py
backend/core/problem_analysis.py
backend/core/qnx_adb_telnet_manager.py
backend/core/qnx_connector.py
backend/core/qnx_manager.py
backend/core/qnx_wexpect_manager.py
backend/core/screen_stream.py
backend/core/shape_discriminator.py
backend/core/simple_chinese_fix.py
backend/core/smart_detector.py
backend/core/temperature_ocr_fix.py
viewscope-1.2.5.dist-info/METADATA
viewscope-1.2.5.dist-info/WHEEL
viewscope-1.2.5.dist-info/entry_points.txt
viewscope-1.2.5.dist-info/top_level.txt
viewscope-1.2.5.dist-info/RECORD
