Metadata-Version: 2.4
Name: viewscope
Version: 1.2.5
Summary: Android UI inspection and automation tool
Home-page: https://github.com/viewscope/viewscope
Author: Sydeng IndieDev
Author-email: s_329379@163.com
License: MIT
Classifier: Development Status :: 4 - Beta
Classifier: Operating System :: Microsoft :: Windows
Classifier: Programming Language :: Python :: 3
Classifier: Programming Language :: Python :: 3.8
Classifier: Programming Language :: Python :: 3.9
Classifier: Programming Language :: Python :: 3.10
Classifier: Programming Language :: Python :: 3.11
Classifier: Programming Language :: Python :: 3.12
Requires-Python: >=3.8
Requires-Dist: fastapi>=0.100.0
Requires-Dist: uvicorn>=0.20.0
Requires-Dist: pydantic>=2.0.0
Requires-Dist: uiautomator2>=3.0.0
Requires-Dist: pillow>=9.0.0
Requires-Dist: adbutils>=2.0.0
Requires-Dist: httpx>=0.24.0
Requires-Dist: websockets>=10.0
Requires-Dist: imagehash>=4.0.0
Dynamic: author
Dynamic: author-email
Dynamic: classifier
Dynamic: home-page
Dynamic: license
Dynamic: requires-dist
Dynamic: requires-python
Dynamic: summary
